pllpython/__init__.py
pllpython/components/__init__.py
pllpython/components/divider.py
pllpython/components/lf.py
pllpython/components/lpd.py
pllpython/components/pll.py
pllpython/components/vco.py
pllpython/utils/__init__.py
pllpython/utils/calculator.py
pllpython/utils/comparators.py
pllpython/utils/formatter.py
pllpython/utils/logger.py
pllpython/utils/scope.py
pllpython/utils/settings.py
pllpython/utils/sweeper.py
pllpython/utils/tutorial.py
pllpython-0.0.9.dist-info/METADATA
pllpython-0.0.9.dist-info/WHEEL
pllpython-0.0.9.dist-info/entry_points.txt
pllpython-0.0.9.dist-info/top_level.txt
pllpython-0.0.9.dist-info/RECORD
