Metadata-Version: 2.1
Name: pllpython
Version: 0.0.9
Requires-Dist: bokeh==3.6.3
Requires-Dist: cmake==3.31.6
Requires-Dist: contourpy==1.3.1
Requires-Dist: cycler==0.12.1
Requires-Dist: exceptiongroup==1.2.2
Requires-Dist: fonttools==4.56.0
Requires-Dist: iniconfig==2.0.0
Requires-Dist: Jinja2==3.1.6
Requires-Dist: kiwisolver==1.4.8
Requires-Dist: MarkupSafe==3.0.2
Requires-Dist: matplotlib==3.10.1
Requires-Dist: numpy==2.2.3
Requires-Dist: packaging==24.2
Requires-Dist: pandas==2.2.3
Requires-Dist: pillow==11.1.0
Requires-Dist: pluggy==1.5.0
Requires-Dist: pyparsing==3.2.1
Requires-Dist: pytest==8.3.4
Requires-Dist: python-dateutil==2.9.0.post0
Requires-Dist: pytz==2025.1
Requires-Dist: PyYAML==6.0.2
Requires-Dist: requests==2.32.3
Requires-Dist: setuptools==65.5.0
Requires-Dist: six==1.17.0
Requires-Dist: scipy==1.15.2
Requires-Dist: serdespy==1.0
Requires-Dist: tomli==2.2.1
Requires-Dist: tornado==6.4.2
Requires-Dist: tqdm==4.67.1
Requires-Dist: twine==6.1.0
Requires-Dist: tzdata==2025.1
Requires-Dist: wheel==0.45.1
Requires-Dist: xyzservices==2025.1.0
